{
	"backtraceGraph" : 
	{
		"commands" : 
		[
			"install",
			"ADD_ELXCOMPONENT"
		],
		"files" : 
		[
			"Components/CMakeLists.txt",
			"Components/Interpolators/BSplineInterpolator/CMakeLists.txt"
		],
		"nodes" : 
		[
			{
				"file" : 1
			},
			{
				"command" : 1,
				"file" : 1,
				"line" : 2,
				"parent" : 0
			},
			{
				"command" : 0,
				"file" : 0,
				"line" : 131,
				"parent" : 1
			}
		]
	},
	"installers" : 
	[
		{
			"backtrace" : 2,
			"component" : "Unspecified",
			"destination" : "lib",
			"paths" : 
			[
				"bin/libBSplineInterpolator-5.1.a"
			],
			"targetId" : "BSplineInterpolator::@6769a37b88a36a6cc6f2",
			"targetIndex" : 11,
			"type" : "target"
		}
	],
	"paths" : 
	{
		"build" : "Components/Interpolators/BSplineInterpolator",
		"source" : "Components/Interpolators/BSplineInterpolator"
	}
}
